{
  "resolvedId": "/Users/rickysitorus/Downloads/Kerja/Pln Icon Plus/valiant-fe/src/services/perbarui-data.ts",
  "transforms": [
    {
      "name": "__load__",
      "result": "import BaseService from \"./base-service\";\n\nconst url = import.meta.env.VITE_API_URL;\n\nexport default class PerbaruiDatService extends BaseService {\n  async getMesinById<T>(id:any): Promise<T> {\n    return this.get(`${url}/mesin-realisasi/${id}`);\n  }\n  async getPembangkitByKode<T>(kode_sentral: string): Promise<T> {\n    return this.get(`${url}pembangkit/by-kode`, {kode_sentral: kode_sentral});\n  }\n  async getPengelolaData<T>(): Promise<T> {\n    return this.get(`${url}filter/combo-pengelola-sentral`);\n  }\n  async getAsumsiParameterData<T>(tahun_realisasi:any, id_mesin:any): Promise<T> {\n    return this.post(`${url}kertas-kerja-detail/asumsi-parameter`, {tahun_realisasi: tahun_realisasi, id_mesin: id_mesin});\n  }\n  async getDataTeknisData<T>(tahun_realisasi:any, id_mesin:any): Promise<T> {\n    return this.post(`${url}kertas-kerja-detail/data-teknis`, {tahun_realisasi: tahun_realisasi, id_mesin: id_mesin});\n  }\n  async getDataTeknisByPeriode<T>(tahun_realisasi:number, id_mesin:number): Promise<T> {\n    return this.post(`${url}kertas-kerja-detail/data-teknis-periode`, {tahun_realisasi: tahun_realisasi, id_mesin: id_mesin});\n  }\n  async getDataFinansialDetail<T>(tahun_realisasi:any, id_mesin:any): Promise<T> {\n    return this.post(`${url}kertas-kerja-detail/data-finansial-detail`, {tahun: tahun_realisasi, id_mesin: id_mesin});\n  }\n  // Data Asumsi Parameter Simulasi 1 & 2 value sama\n  async getAsumsiParameterSimulasi<T>(tahun_realisasi: any, id_mesin: any): Promise<T> {\n    return this.post(`${url}kertas-kerja-detail/asumsi-parameter-simulasi`, {tahun_realisasi: tahun_realisasi, id_mesin: id_mesin});\n  }\n  // Data Teknis Simulasi 1\n  async getDataTeknisSimulasi1<T>(tahun_realisasi: any, id_mesin: any): Promise<T> {\n    return this.post(`${url}kertas-kerja-detail/data-finansial-detail`, {tahun_realisasi: tahun_realisasi, id_mesin: id_mesin});\n  }\n  // Data Teknis Simulasi 2\n  async getDataTeknisSimulasi2<T>(tahun_realisasi: any, id_mesin: any): Promise<T> {\n    return this.post(`${url}kertas-kerja-detail/data-finansial-detail`, {tahun_realisasi: tahun_realisasi, id_mesin: id_mesin});\n  }\n  // Data Finansial Simulasi 1\n  async getDataFinansialSimulasi1<T>(tahun_realisasi: any, id_mesin: any): Promise<T> {\n    return this.post(`${url}kertas-kerja-detail/data-finansial-detail`, {tahun_realisasi: tahun_realisasi, id_mesin: id_mesin});\n  }\n  // Data Finansial Simulasi 2\n  async getDataFinansialSimulasi2<T>(tahun_realisasi: any, id_mesin: any): Promise<T> {\n    return this.post(`${url}kertas-kerja-detail/data-finansial-detail`, {tahun_realisasi: tahun_realisasi, id_mesin: id_mesin});\n  }\n  async getComboTypePeriodicData<T>(jenis_pembangkit:any): Promise<T> {\n    return this.get(`${url}filter/combo-type-periodic`, {jenis_pembangkit: jenis_pembangkit});\n  }\n  async updateAsumsiMakro<T>(form_data:any): Promise<T> {\n    return this.post(`${url}kertas-kerja-detail/asumsi-wacc-update`, form_data);\n  }\n  async updateParameterTeknis<T>(form_data:any): Promise<T> {\n    return this.post(`${url}kertas-kerja-detail/parameter-finansial`, form_data);\n  }\n  async updateDataTeknis<T>(form_data:any): Promise<T> {\n    return this.post(`${url}kertas-kerja-detail/data-teknis-create`, form_data);\n  }\n  async getTypePeriodic<T>(kode_jenis_pembangkit:any): Promise<T> {\n    return this.get(`${url}kertas-kerja-detail/type-periodic`, {kode_jenis_pembangkit: kode_jenis_pembangkit});\n  }\n  async getComboBahanBakar<T>(jenis_pembangkit:any): Promise<T> {\n    return this.get(`${url}filter/combo-bahan-bakar`, {jenis_pembangkit: jenis_pembangkit});\n  }\n}\n",
      "start": 1709026302600,
      "end": 1709026302600
    },
    {
      "name": "vite:esbuild",
      "result": "import BaseService from \"./base-service\";\nconst url = import.meta.env.VITE_API_URL;\nexport default class PerbaruiDatService extends BaseService {\n  async getMesinById(id) {\n    return this.get(`${url}/mesin-realisasi/${id}`);\n  }\n  async getPembangkitByKode(kode_sentral) {\n    return this.get(`${url}pembangkit/by-kode`, { kode_sentral });\n  }\n  async getPengelolaData() {\n    return this.get(`${url}filter/combo-pengelola-sentral`);\n  }\n  async getAsumsiParameterData(tahun_realisasi, id_mesin) {\n    return this.post(`${url}kertas-kerja-detail/asumsi-parameter`, { tahun_realisasi, id_mesin });\n  }\n  async getDataTeknisData(tahun_realisasi, id_mesin) {\n    return this.post(`${url}kertas-kerja-detail/data-teknis`, { tahun_realisasi, id_mesin });\n  }\n  async getDataTeknisByPeriode(tahun_realisasi, id_mesin) {\n    return this.post(`${url}kertas-kerja-detail/data-teknis-periode`, { tahun_realisasi, id_mesin });\n  }\n  async getDataFinansialDetail(tahun_realisasi, id_mesin) {\n    return this.post(`${url}kertas-kerja-detail/data-finansial-detail`, { tahun: tahun_realisasi, id_mesin });\n  }\n  // Data Asumsi Parameter Simulasi 1 & 2 value sama\n  async getAsumsiParameterSimulasi(tahun_realisasi, id_mesin) {\n    return this.post(`${url}kertas-kerja-detail/asumsi-parameter-simulasi`, { tahun_realisasi, id_mesin });\n  }\n  // Data Teknis Simulasi 1\n  async getDataTeknisSimulasi1(tahun_realisasi, id_mesin) {\n    return this.post(`${url}kertas-kerja-detail/data-finansial-detail`, { tahun_realisasi, id_mesin });\n  }\n  // Data Teknis Simulasi 2\n  async getDataTeknisSimulasi2(tahun_realisasi, id_mesin) {\n    return this.post(`${url}kertas-kerja-detail/data-finansial-detail`, { tahun_realisasi, id_mesin });\n  }\n  // Data Finansial Simulasi 1\n  async getDataFinansialSimulasi1(tahun_realisasi, id_mesin) {\n    return this.post(`${url}kertas-kerja-detail/data-finansial-detail`, { tahun_realisasi, id_mesin });\n  }\n  // Data Finansial Simulasi 2\n  async getDataFinansialSimulasi2(tahun_realisasi, id_mesin) {\n    return this.post(`${url}kertas-kerja-detail/data-finansial-detail`, { tahun_realisasi, id_mesin });\n  }\n  async getComboTypePeriodicData(jenis_pembangkit) {\n    return this.get(`${url}filter/combo-type-periodic`, { jenis_pembangkit });\n  }\n  async updateAsumsiMakro(form_data) {\n    return this.post(`${url}kertas-kerja-detail/asumsi-wacc-update`, form_data);\n  }\n  async updateParameterTeknis(form_data) {\n    return this.post(`${url}kertas-kerja-detail/parameter-finansial`, form_data);\n  }\n  async updateDataTeknis(form_data) {\n    return this.post(`${url}kertas-kerja-detail/data-teknis-create`, form_data);\n  }\n  async getTypePeriodic(kode_jenis_pembangkit) {\n    return this.get(`${url}kertas-kerja-detail/type-periodic`, { kode_jenis_pembangkit });\n  }\n  async getComboBahanBakar(jenis_pembangkit) {\n    return this.get(`${url}filter/combo-bahan-bakar`, { jenis_pembangkit });\n  }\n}\n",
      "start": 1709026302600,
      "end": 1709026302665,
      "order": "normal"
    },
    {
      "name": "vite:import-analysis",
      "result": "import.meta.env = {\"VITE_API_URL\":\"https://portalapp.iconpln.co.id:5080/valiant-be/v1/\",\"VITE_USER_NODE_ENV\":\"development\",\"BASE_URL\":\"/\",\"MODE\":\"development\",\"DEV\":true,\"PROD\":false,\"SSR\":false};import BaseService from \"/src/services/base-service.ts?t=1709026301545\";\nconst url = import.meta.env.VITE_API_URL;\nexport default class PerbaruiDatService extends BaseService {\n  async getMesinById(id) {\n    return this.get(`${url}/mesin-realisasi/${id}`);\n  }\n  async getPembangkitByKode(kode_sentral) {\n    return this.get(`${url}pembangkit/by-kode`, { kode_sentral });\n  }\n  async getPengelolaData() {\n    return this.get(`${url}filter/combo-pengelola-sentral`);\n  }\n  async getAsumsiParameterData(tahun_realisasi, id_mesin) {\n    return this.post(`${url}kertas-kerja-detail/asumsi-parameter`, { tahun_realisasi, id_mesin });\n  }\n  async getDataTeknisData(tahun_realisasi, id_mesin) {\n    return this.post(`${url}kertas-kerja-detail/data-teknis`, { tahun_realisasi, id_mesin });\n  }\n  async getDataTeknisByPeriode(tahun_realisasi, id_mesin) {\n    return this.post(`${url}kertas-kerja-detail/data-teknis-periode`, { tahun_realisasi, id_mesin });\n  }\n  async getDataFinansialDetail(tahun_realisasi, id_mesin) {\n    return this.post(`${url}kertas-kerja-detail/data-finansial-detail`, { tahun: tahun_realisasi, id_mesin });\n  }\n  // Data Asumsi Parameter Simulasi 1 & 2 value sama\n  async getAsumsiParameterSimulasi(tahun_realisasi, id_mesin) {\n    return this.post(`${url}kertas-kerja-detail/asumsi-parameter-simulasi`, { tahun_realisasi, id_mesin });\n  }\n  // Data Teknis Simulasi 1\n  async getDataTeknisSimulasi1(tahun_realisasi, id_mesin) {\n    return this.post(`${url}kertas-kerja-detail/data-finansial-detail`, { tahun_realisasi, id_mesin });\n  }\n  // Data Teknis Simulasi 2\n  async getDataTeknisSimulasi2(tahun_realisasi, id_mesin) {\n    return this.post(`${url}kertas-kerja-detail/data-finansial-detail`, { tahun_realisasi, id_mesin });\n  }\n  // Data Finansial Simulasi 1\n  async getDataFinansialSimulasi1(tahun_realisasi, id_mesin) {\n    return this.post(`${url}kertas-kerja-detail/data-finansial-detail`, { tahun_realisasi, id_mesin });\n  }\n  // Data Finansial Simulasi 2\n  async getDataFinansialSimulasi2(tahun_realisasi, id_mesin) {\n    return this.post(`${url}kertas-kerja-detail/data-finansial-detail`, { tahun_realisasi, id_mesin });\n  }\n  async getComboTypePeriodicData(jenis_pembangkit) {\n    return this.get(`${url}filter/combo-type-periodic`, { jenis_pembangkit });\n  }\n  async updateAsumsiMakro(form_data) {\n    return this.post(`${url}kertas-kerja-detail/asumsi-wacc-update`, form_data);\n  }\n  async updateParameterTeknis(form_data) {\n    return this.post(`${url}kertas-kerja-detail/parameter-finansial`, form_data);\n  }\n  async updateDataTeknis(form_data) {\n    return this.post(`${url}kertas-kerja-detail/data-teknis-create`, form_data);\n  }\n  async getTypePeriodic(kode_jenis_pembangkit) {\n    return this.get(`${url}kertas-kerja-detail/type-periodic`, { kode_jenis_pembangkit });\n  }\n  async getComboBahanBakar(jenis_pembangkit) {\n    return this.get(`${url}filter/combo-bahan-bakar`, { jenis_pembangkit });\n  }\n}\n",
      "start": 1709026302665,
      "end": 1709026302665,
      "order": "normal"
    }
  ]
}
